README.md
setup.py
qcli/__init__.py
qcli/common.py
qcli/bsp2svg/__init__.py
qcli/bsp2svg/api.py
qcli/bsp2svg/cli.py
qcli/bsp2svg/converter.py
qcli/bsp2wad/__init__.py
qcli/bsp2wad/cli.py
qcli/image2spr/__init__.py
qcli/image2spr/cli.py
qcli/pak/__init__.py
qcli/pak/cli.py
qcli/qmount/__init__.py
qcli/qmount/cli.py
qcli/qmount/handlers.py
qcli/qmount/platforms.py
qcli/spr2image/__init__.py
qcli/spr2image/cli.py
qcli/unpak/__init__.py
qcli/unpak/cli.py
qcli/unwad/__init__.py
qcli/unwad/cli.py
qcli/wad/__init__.py
qcli/wad/cli.py
quake_cli_tools.egg-info/PKG-INFO
quake_cli_tools.egg-info/SOURCES.txt
quake_cli_tools.egg-info/dependency_links.txt
quake_cli_tools.egg-info/entry_points.txt
quake_cli_tools.egg-info/requires.txt
quake_cli_tools.egg-info/top_level.txt