Metadata-Version: 2.1
Name: quake-cli-tools
Version: 1.2.0
Summary: UNKNOWN
Home-page: https://github.com/JoshuaSkelly/quake-cli-tools
Author: Joshua Skelton
Author-email: joshua.skelton@gmail.com
License: MIT
Platform: UNKNOWN
Classifier: Intended Audience :: Developers
Classifier: License :: OSI Approved :: MIT License
Classifier: Operating System :: OS Independent
Classifier: Programming Language :: Python
Classifier: Programming Language :: Python :: 3.7
Requires-Python: >=3.6
